sai_mujoco/__init__.py
sai_mujoco/assets/bases/v0/floating_legged_base.xml
sai_mujoco/assets/bases/v0/no_actuation_base.xml
sai_mujoco/assets/bases/v0/null_base.xml
sai_mujoco/assets/bases/v0/null_mobile_base.xml
sai_mujoco/assets/bases/v0/null_mount.xml
sai_mujoco/assets/bases/v0/omron_mobile_base.xml
sai_mujoco/assets/bases/v0/rethink_mount.xml
sai_mujoco/assets/bases/v0/rethink_mount_scaled.xml
sai_mujoco/assets/bases/v0/meshes/omron_mobile_base/omron_0.obj
sai_mujoco/assets/bases/v0/meshes/omron_mobile_base/omron_1.obj
sai_mujoco/assets/bases/v0/meshes/omron_mobile_base/omron_2.obj
sai_mujoco/assets/bases/v0/meshes/omron_mobile_base/omron_3.obj
sai_mujoco/assets/bases/v0/meshes/omron_mobile_base/omron_4.obj
sai_mujoco/assets/bases/v0/meshes/omron_mobile_base/omron_5.obj
sai_mujoco/assets/bases/v0/meshes/omron_mobile_base/omron_6.obj
sai_mujoco/assets/bases/v0/meshes/omron_mobile_base/omron_7.obj
sai_mujoco/assets/bases/v0/meshes/rethink_mount/pedestal.dae
sai_mujoco/assets/bases/v0/meshes/rethink_mount/pedestal.mtl
sai_mujoco/assets/bases/v0/meshes/rethink_mount/pedestal.obj
sai_mujoco/assets/bases/v0/meshes/rethink_mount/pedestal.stl
sai_mujoco/assets/envs/football/meshes/ArenaX_Black.png
sai_mujoco/assets/envs/football/meshes/ArenaX_Labs.png
sai_mujoco/assets/envs/football/meshes/defender.obj
sai_mujoco/assets/envs/football/meshes/goal_north.obj
sai_mujoco/assets/envs/football/meshes/goalkeeper.mtl
sai_mujoco/assets/envs/football/meshes/goalkeeper.obj
sai_mujoco/assets/envs/football/meshes/goalkeeper.png
sai_mujoco/assets/envs/football/meshes/pitch_l.obj
sai_mujoco/assets/envs/football/meshes/soccer/back.png
sai_mujoco/assets/envs/football/meshes/soccer/down.png
sai_mujoco/assets/envs/football/meshes/soccer/front.png
sai_mujoco/assets/envs/football/meshes/soccer/left.png
sai_mujoco/assets/envs/football/meshes/soccer/right.png
sai_mujoco/assets/envs/football/meshes/soccer/up.png
sai_mujoco/assets/envs/football/v0/env.xml
sai_mujoco-0.1.30.dist-info/METADATA
sai_mujoco-0.1.30.dist-info/WHEEL
sai_mujoco-0.1.30.dist-info/licenses/LICENSE
sai_mujoco-0.1.30.dist-info/RECORD
